README.rst
flask_github.py
setup.py
GitHub_Flask.egg-info/PKG-INFO
GitHub_Flask.egg-info/SOURCES.txt
GitHub_Flask.egg-info/dependency_links.txt
GitHub_Flask.egg-info/not-zip-safe
GitHub_Flask.egg-info/pbr.json
GitHub_Flask.egg-info/requires.txt
GitHub_Flask.egg-info/top_level.txt