Metadata-Version: 1.1
Name: GitHub-Flask
Version: 3.1.1
Summary: GitHub extension for Flask microframework
Home-page: http://github.com/cenkalti/github-flask
Author: Cenk Alti
Author-email: cenkalti@gmail.com
License: MIT
Platform: any
Classifier: Environment :: Web Environment
Classifier: Intended Audience :: Developers
Classifier: Operating System :: OS Independent
Classifier: Programming Language :: Python
Classifier: Topic :: Internet :: WWW/HTTP :: Dynamic Content
Classifier: Topic :: Software Development :: Libraries :: Python Modules
